{
  "blogs": [
    {
      "id": "b81d",
      "title": "Moms",
      "body": "Nowadays kigali moms are always looking out for jobs which may faccilitate their lives to make them good",
      "author": "Mario"
    },
    {
      "id": "7b7e",
      "title": "sdlfj",
      "body": "yoshi is sdlkdsassdds",
      "author": "yoshi"
    },
    {
      "id": "464d",
      "title": "Gaby",
      "body": "Who is the person who gave him something like this so that he could create one for me",
      "author": "Mario"
    }
  ]
}